<?xml version="1.0" encoding="UTF-8"?>
<tei xmlns="http://www.tei-c.org/ns/1.0" xmlns:xlink="http://www.w3.org/1999/xlink" xmlns:mml="http://www.w3.org/1998/Math/MathML">
	<teiHeader>
		<fileDesc>
			<sourceDesc>
				<biblStruct>
					<analytic>
						<author>

						<affiliation>
							<orgName type="institution">Henkel Corporation</orgName>
							<lb/>
							<orgName type="institution">Aerospace Group</orgName>
							<lb/>
							<address>
								<addrLine>2850 Willow Pass Road</addrLine>
							<lb/>
								<postBox>P.O. Box 312</postBox>
							<lb/>
								<settlement>Bay Point</settlement>,
								<region>CA</region>
								<postCode>94565</postCode>
								<country>USA</country>
							</address>
						</affiliation>

						</author>
					</analytic>
				</biblStruct>
			</sourceDesc>
		</fileDesc>
	</teiHeader>
</tei>
