<?xml version="1.0" encoding="UTF-8"?>
<tei xmlns="http://www.tei-c.org/ns/1.0" xmlns:xlink="http://www.w3.org/1999/xlink" xmlns:mml="http://www.w3.org/1998/Math/MathML">
	<teiHeader>
		<fileDesc>
			<sourceDesc>
				<biblStruct>
					<analytic>
						<author>

						<affiliation>
							<orgName type="department">Institute of Nutrition of Central America and Panama (INCAP)</orgName>,
							<address>
								<postBox>P. 0. Box 1188</postBox>,
								<settlement>Guatemala</settlement>,
								<country>Guatemala</country>,
								<region>C.A.</region>
							</address>
						</affiliation>

						</author>
					</analytic>
				</biblStruct>
			</sourceDesc>
		</fileDesc>
	</teiHeader>
</tei>
