<?xml version="1.0" encoding="UTF-8"?>
<tei xmlns="http://www.tei-c.org/ns/1.0" xmlns:xlink="http://www.w3.org/1999/xlink" xmlns:mml="http://www.w3.org/1998/Math/MathML">
	<teiHeader>
		<fileDesc>
			<sourceDesc>
				<biblStruct>
					<analytic>
						<author>

						<affiliation>
							<orgName type="laboratory">Labor für Informatik (LFI) Labor für Informatik (LFI)</orgName>
							<lb/>
						</affiliation>
						<affiliation>									
							<orgName type="institution">Labor für Informatik (LFI) -FB M -Hochschule Bochum</orgName>
						</affiliation>

						</author>
					</analytic>
				</biblStruct>
			</sourceDesc>
		</fileDesc>
	</teiHeader>
</tei>
